    {
  "username": "",
  "password": "",
  "ip": "epic-shard.com",
  "port": 5003,
  "ultimaonlinedirectory": "../",
  "profilespath": "",
  "clientversion": "7.0.60.47",
  "lang": "ENG",
  "lastservernum": 1,
  "last_server_name": "Epic! Shard",
  "fps": 60,
  "window_position": {
    "X": 814,
    "Y": 166
  },
  "window_size": {
    "X": 2560,
    "Y": 1369
  },
  "is_win_maximized": true,
  "saveaccount": true,
  "autologin": false,
  "reconnect": false,
  "reconnect_time": 0,
  "login_music": false,
  "login_music_volume": 50,
  "shard_type": 0,
  "fixed_time_step": true,
  "run_mouse_in_separate_thread": true,
  "force_driver": 0,
  "use_verdata": false,
  "maps_layouts": null,
  "encryption": 5,
  "plugins": [

  ]
}